odoo10_addon_crm_claim-10.0.1.0.0.99.dev26-py3.8-nspkg.pth
odoo/addons/crm_claim/README.rst
odoo/addons/crm_claim/__init__.py
odoo/addons/crm_claim/__manifest__.py
odoo/addons/crm_claim/data/crm_claim_data.xml
odoo/addons/crm_claim/demo/crm_claim_demo.xml
odoo/addons/crm_claim/i18n/am.po
odoo/addons/crm_claim/i18n/ar.po
odoo/addons/crm_claim/i18n/bg.po
odoo/addons/crm_claim/i18n/bs.po
odoo/addons/crm_claim/i18n/ca.po
odoo/addons/crm_claim/i18n/crm_claim.pot
odoo/addons/crm_claim/i18n/cs.po
odoo/addons/crm_claim/i18n/da.po
odoo/addons/crm_claim/i18n/de.po
odoo/addons/crm_claim/i18n/el_GR.po
odoo/addons/crm_claim/i18n/en_GB.po
odoo/addons/crm_claim/i18n/es.po
odoo/addons/crm_claim/i18n/es_AR.po
odoo/addons/crm_claim/i18n/es_CL.po
odoo/addons/crm_claim/i18n/es_CO.po
odoo/addons/crm_claim/i18n/es_CR.po
odoo/addons/crm_claim/i18n/es_DO.po
odoo/addons/crm_claim/i18n/es_EC.po
odoo/addons/crm_claim/i18n/es_ES.po
odoo/addons/crm_claim/i18n/es_MX.po
odoo/addons/crm_claim/i18n/es_PE.po
odoo/addons/crm_claim/i18n/es_PY.po
odoo/addons/crm_claim/i18n/es_VE.po
odoo/addons/crm_claim/i18n/et.po
odoo/addons/crm_claim/i18n/eu.po
odoo/addons/crm_claim/i18n/fa.po
odoo/addons/crm_claim/i18n/fi.po
odoo/addons/crm_claim/i18n/fr.po
odoo/addons/crm_claim/i18n/fr_CA.po
odoo/addons/crm_claim/i18n/fr_CH.po
odoo/addons/crm_claim/i18n/gl.po
odoo/addons/crm_claim/i18n/gl_ES.po
odoo/addons/crm_claim/i18n/he.po
odoo/addons/crm_claim/i18n/hr.po
odoo/addons/crm_claim/i18n/hr_HR.po
odoo/addons/crm_claim/i18n/hu.po
odoo/addons/crm_claim/i18n/id.po
odoo/addons/crm_claim/i18n/it.po
odoo/addons/crm_claim/i18n/ja.po
odoo/addons/crm_claim/i18n/ko.po
odoo/addons/crm_claim/i18n/lt.po
odoo/addons/crm_claim/i18n/lt_LT.po
odoo/addons/crm_claim/i18n/lv.po
odoo/addons/crm_claim/i18n/mk.po
odoo/addons/crm_claim/i18n/mn.po
odoo/addons/crm_claim/i18n/nb.po
odoo/addons/crm_claim/i18n/nb_NO.po
odoo/addons/crm_claim/i18n/nl.po
odoo/addons/crm_claim/i18n/nl_BE.po
odoo/addons/crm_claim/i18n/nl_NL.po
odoo10_addon_crm_claim-10.0.1.0.0.99.dev26.dist-info/METADATA
odoo10_addon_crm_claim-10.0.1.0.0.99.dev26.dist-info/WHEEL
odoo10_addon_crm_claim-10.0.1.0.0.99.dev26.dist-info/namespace_packages.txt
odoo10_addon_crm_claim-10.0.1.0.0.99.dev26.dist-info/top_level.txt
odoo10_addon_crm_claim-10.0.1.0.0.99.dev26.dist-info/RECORD
